setup.py
article_recommender/__init__.py
article_recommender/recommender.py
article_recommender/recommender_helper_functions.py
article_recommender.egg-info/PKG-INFO
article_recommender.egg-info/SOURCES.txt
article_recommender.egg-info/dependency_links.txt
article_recommender.egg-info/not-zip-safe
article_recommender.egg-info/top_level.txt