Metadata-Version: 1.0
Name: article-recommender
Version: 1.0.4
Summary: Create a recommendation engine for articles
Home-page: UNKNOWN
Author: Celestin Hermez
Author-email: celestinhermez@gmail.com
License: UNKNOWN
Platform: UNKNOWN
